atla/__init__.py
atla/_base_client.py
atla/_client.py
atla/_compat.py
atla/_constants.py
atla/_exceptions.py
atla/_files.py
atla/_models.py
atla/_qs.py
atla/_resource.py
atla/_response.py
atla/_streaming.py
atla/_types.py
atla/_version.py
atla/py.typed
atla/_utils/__init__.py
atla/_utils/_logs.py
atla/_utils/_proxy.py
atla/_utils/_reflection.py
atla/_utils/_streams.py
atla/_utils/_sync.py
atla/_utils/_transform.py
atla/_utils/_typing.py
atla/_utils/_utils.py
atla/lib/.keep
atla/resources/__init__.py
atla/resources/evaluation.py
atla/resources/chat/__init__.py
atla/resources/chat/chat.py
atla/resources/chat/completions.py
atla/resources/metrics/__init__.py
atla/resources/metrics/few_shot_examples.py
atla/resources/metrics/metrics.py
atla/resources/metrics/prompts.py
atla/types/__init__.py
atla/types/chat_completion.py
atla/types/evaluation.py
atla/types/evaluation_create_params.py
atla/types/metric.py
atla/types/metric_create_params.py
atla/types/metric_create_response.py
atla/types/metric_delete_response.py
atla/types/metric_get_response.py
atla/types/metric_list_params.py
atla/types/metric_list_response.py
atla/types/chat/__init__.py
atla/types/chat/completion_create_params.py
atla/types/metrics/__init__.py
atla/types/metrics/few_shot_example.py
atla/types/metrics/few_shot_example_param.py
atla/types/metrics/few_shot_example_set_params.py
atla/types/metrics/few_shot_example_set_response.py
atla/types/metrics/prompt.py
atla/types/metrics/prompt_create_params.py
atla/types/metrics/prompt_create_response.py
atla/types/metrics/prompt_get_response.py
atla/types/metrics/prompt_list_response.py
atla/types/metrics/prompt_set_active_prompt_version_params.py
atla/types/metrics/prompt_set_active_prompt_version_response.py
atla-0.6.2.dist-info/METADATA
atla-0.6.2.dist-info/WHEEL
atla-0.6.2.dist-info/licenses/LICENSE
atla-0.6.2.dist-info/RECORD
